SimpleUserManager-0.1.dist-info/DESCRIPTION.rst
SimpleUserManager-0.1.dist-info/METADATA
SimpleUserManager-0.1.dist-info/RECORD
SimpleUserManager-0.1.dist-info/WHEEL
SimpleUserManager-0.1.dist-info/metadata.json
SimpleUserManager-0.1.dist-info/top_level.txt
user_manager/__init__.py
user_manager/manager.py
