Metadata-Version: 2.0
Name: SimpleUserManager
Version: 0.1
Summary: A simple user manager and user library
Home-page: UNKNOWN
Author: powersc5
Author-email: powersc5@nku.edu
License: UNKNOWN
Platform: UNKNOWN
